fluent/__init__.py
fluent/pygments/__init__.py
fluent/pygments/cli.py
fluent/pygments/lexer.py
fluent.pygments-1.0.dist-info/METADATA
fluent.pygments-1.0.dist-info/WHEEL
fluent.pygments-1.0.dist-info/entry_points.txt
fluent.pygments-1.0.dist-info/top_level.txt
fluent.pygments-1.0.dist-info/RECORD
