Metadata-Version: 2.1
Name: fluent.pygments
Version: 1.0
Summary: Pygments lexer for Fluent.
Home-page: https://github.com/projectfluent/python-fluent
Author: Mozilla
Author-email: l10n-drivers@mozilla.org
License: APL 2
Keywords: fluent,pygments
Platform: UNKNOWN
Classifier: Development Status :: 3 - Alpha
Classifier: Intended Audience :: Developers
Classifier: License :: OSI Approved :: Apache Software License
Classifier: Programming Language :: Python :: 2.7
Classifier: Programming Language :: Python :: 3.5
Requires-Dist: pygments
Requires-Dist: fluent.syntax
Requires-Dist: six
